analyzeAudio/__init__.py
analyzeAudio/analyzersUseFilename.py
analyzeAudio/analyzersUseSpectrogram.py
analyzeAudio/analyzersUseTensor.py
analyzeAudio/analyzersUseWaveform.py
analyzeAudio/audioAspectsRegistry.py
analyzeAudio/py.typed
analyzeAudio/pythonator.py
analyzeaudio-0.0.17.dist-info/licenses/LICENSE
tests/conftest.py
tests/test_audioAspectsRegistry.py
tests/test_other.py
analyzeaudio-0.0.17.dist-info/METADATA
analyzeaudio-0.0.17.dist-info/WHEEL
analyzeaudio-0.0.17.dist-info/entry_points.txt
analyzeaudio-0.0.17.dist-info/top_level.txt
analyzeaudio-0.0.17.dist-info/RECORD
