Metadata-Version: 2.4
Name: analyzeAudio
Version: 0.0.17
Summary: Measure one or more aspects of one or more audio files.
Author-email: Hunter Hogan <HunterHogan@pm.me>
License: CC-BY-NC-4.0
Project-URL: Donate, https://www.patreon.com/integrated
Project-URL: Homepage, https://github.com/hunterhogan/analyzeAudio
Project-URL: Issues, https://github.com/hunterhogan/
Project-URL: Repository, https://github.com/hunterhogan/analyzeAudio.git
Keywords: FFmpeg,FFprobe,LUFS,RMS,SRMR,analysis,audio,audio-analysis,loudness,measurement,metrics,signal-processing,spectral,spectrum,torch,waveform
Classifier: Development Status :: 3 - Alpha
Classifier: Environment :: Console
Classifier: Intended Audience :: Developers
Classifier: Intended Audience :: End Users/Desktop
Classifier: Intended Audience :: Information Technology
Classifier: Intended Audience :: Other Audience
Classifier: Intended Audience :: Science/Research
Classifier: Natural Language :: English
Classifier: Operating System :: OS Independent
Classifier: Programming Language :: Python
Classifier: Programming Language :: Python :: 3
Classifier: Programming Language :: Python :: 3.10
Classifier: Programming Language :: Python :: 3.11
Classifier: Programming Language :: Python :: 3.12
Classifier: Programming Language :: Python :: 3.13
Classifier: Topic :: Multimedia :: Sound/Audio
Classifier: Topic :: Multimedia :: Sound/Audio :: Analysis
Classifier: Topic :: Multimedia :: Sound/Audio :: Conversion
Classifier: Topic :: Scientific/Engineering :: Information Analysis
Classifier: Topic :: Software Development :: Libraries :: Python Modules
Classifier: Typing :: Typed
Requires-Python: >=3.10
License-File: LICENSE
Requires-Dist: Z0Z_tools
Requires-Dist: cachetools
Requires-Dist: hunterMakesPy
Requires-Dist: librosa
Requires-Dist: numpy
Requires-Dist: standard-aifc; python_version >= "3.13"
Requires-Dist: standard-sunau; python_version >= "3.13"
Requires-Dist: torch
Requires-Dist: torchmetrics[audio]
Requires-Dist: tqdm
Requires-Dist: typing_extensions
Provides-Extra: testing
Requires-Dist: pytest; extra == "testing"
Requires-Dist: pytest-cov; extra == "testing"
Requires-Dist: pytest-xdist; extra == "testing"
Requires-Dist: pyupgrade; extra == "testing"
Dynamic: license-file
